darum/__init__.py
darum/compare_distribution.py
darum/dafny_measure.py
darum/find_extremes.py
darum/log_readers.py
darum/plot_distribution.py
darum-1.0.1.dist-info/LICENSE
darum-1.0.1.dist-info/METADATA
darum-1.0.1.dist-info/WHEEL
darum-1.0.1.dist-info/entry_points.txt
darum-1.0.1.dist-info/RECORD
