Metadata-Version: 2.3
Name: darum
Version: 1.0.1
Summary: DAfny Resource Usage Measurement
Author: Horacio Mijail Anton Quiles
Author-email: hmijail@gmail.com
Requires-Python: >=3.12,<4.0
Classifier: Programming Language :: Python :: 3
Classifier: Programming Language :: Python :: 3.12
Classifier: Programming Language :: Python :: 3.13
Requires-Dist: ansi2html (>=1.9.2)
Requires-Dist: hvplot (>=0.9.2)
Requires-Dist: psutil (>=6.0.0)
Requires-Dist: pygments (>=2.18.0)
Requires-Dist: quantiphy (>=2.19)
Requires-Dist: sh (>=2.0.7)
